{
    "version": "2.25",
    "description": "bnetlauncher - Battle.net Launcher for Windows",
    "homepage": "https://github.com/dafzor/bnetlauncher",
    "license": "MIT",
    "architecture": {
        "64bit": {
            "url": "https://github.com/dafzor/bnetlauncher/releases/download/v2.25/bnetlauncher_v225.zip",
            "hash": "2978933051f1265fafc3e7a19d5f2eeec5e2fb6c1c34e199dc0995c054cee0d9"
        }
    },
    "bin": "bnetlauncher.exe",
    "checkver": {
        "github": "https://github.com/dafzor/bnetlauncher"
    },
    "autoupdate": {
        "architecture": {
            "64bit": {
                "url": "https://github.com/dafzor/bnetlauncher/releases/download/v$version/bnetlauncher_v$cleanVersion.zip"
            }
        }
    }
}
