{
    "version": "1.2.1",
    "description": "ITGmania is a community-driven rhythm game and fork of StepMania",
    "homepage": "https://github.com/itgmania/itgmania",
    "license": "MIT",
    "architecture": {
        "64bit": {
            "url": "https://github.com/itgmania/itgmania/releases/download/v1.2.1/ITGmania-1.2.1-portable.zip",
            "hash": "d11bcdc20d30d61d271eaa5d1272660abbc1a7038559cc5f2e2504991eaf2435"
        }
    },
    "persist": "itgmania\\Save",
    "bin": "itgmania\\Program\\ITGmania.exe",
    "shortcuts": [
        [
            "itgmania\\Program\\ITGmania.exe",
            "ITGmania"
        ]
    ],
    "checkver": {
        "github": "https://github.com/itgmania/itgmania"
    },
    "autoupdate": {
        "architecture": {
            "64bit": {
                "url": "https://github.com/itgmania/itgmania/releases/download/v$version/ITGmania-$version-portable.zip"
            }
        }
    }
}
